odin_bot_exchanges/__init__.py
odin_bot_exchanges/binance/__init__.py
odin_bot_exchanges/binance/account.py
odin_bot_exchanges/binance/client.py
odin_bot_exchanges/binance/responses.py
odin_bot_exchanges/binance/trades.py
odin_bot_exchanges/currency.py
odin_bot_exchanges/exchange.py
odin_bot_exchanges/kraken/__init__.py
odin_bot_exchanges/kraken/client.py
odin_bot_exchanges/kraken/currency.py
odin_bot_exchanges/kraken/responses.py
odin_bot_exchanges/orionx/__init__.py
odin_bot_exchanges/orionx/responses.py
odin_bot_exchanges/responses.py
odin_bot_exchanges-0.7.2.dist-info/WHEEL
odin_bot_exchanges-0.7.2.dist-info/METADATA
odin_bot_exchanges-0.7.2.dist-info/RECORD
