Metadata-Version: 2.1
Name: odin-bot-exchanges
Version: 0.7.2
Summary: 
Author: adolfrodeno
Author-email: amvillalobos@uc.cl
Requires-Python: >=3.8,<4.0
Classifier: Programming Language :: Python :: 3
Classifier: Programming Language :: Python :: 3.10
Classifier: Programming Language :: Python :: 3.8
Classifier: Programming Language :: Python :: 3.9
Requires-Dist: binance-connector (>=1.9.0,<2.0.0)
Requires-Dist: odin-bot-entities (>=0.2.0,<0.3.0)
Requires-Dist: orionx-python-client (>=0.4.0,<0.5.0)
Requires-Dist: python-dotenv (>=0.19.1,<0.20.0)
